pystromligning/__init__.py
pystromligning/const.py
pystromligning/exceptions.py
pystromligning-0.1.4.dist-info/LICENSE
pystromligning-0.1.4.dist-info/METADATA
pystromligning-0.1.4.dist-info/WHEEL
pystromligning-0.1.4.dist-info/RECORD
