Metadata-Version: 2.3
Name: pystromligning
Version: 0.1.4
Summary: Library for communicating with the Stromligning API
License: MIT
Author: Malene Trab
Author-email: malene@trab.dk
Requires-Python: >=3.11,<4.0
Classifier: License :: OSI Approved :: MIT License
Classifier: Programming Language :: Python :: 3
Classifier: Programming Language :: Python :: 3.11
Classifier: Programming Language :: Python :: 3.12
Classifier: Programming Language :: Python :: 3.13
Requires-Dist: requests (>=2.32.0,<3.0.0)
